[
  {
    "name": "197780",
    "href": "197780.html",
    "type": "file"
  },
  {
    "name": "197781",
    "href": "197781.html",
    "type": "file"
  },
  {
    "name": "197782",
    "href": "197782.html",
    "type": "file"
  },
  {
    "name": "197783",
    "href": "197783.html",
    "type": "file"
  },
  {
    "name": "197784",
    "href": "197784.html",
    "type": "file"
  },
  {
    "name": "197786",
    "href": "197786.html",
    "type": "file"
  },
  {
    "name": "197788",
    "href": "197788.html",
    "type": "file"
  },
  {
    "name": "197790",
    "href": "197790.html",
    "type": "file"
  },
  {
    "name": "197791",
    "href": "197791.html",
    "type": "file"
  },
  {
    "name": "197792",
    "href": "197792.html",
    "type": "file"
  },
  {
    "name": "197793",
    "href": "197793.html",
    "type": "file"
  },
  {
    "name": "197794",
    "href": "197794.html",
    "type": "file"
  }
]